hkopenai/hk_health_mcp_server/__init__.py
hkopenai/hk_health_mcp_server/__main__.py
hkopenai/hk_health_mcp_server/app.py
hkopenai/hk_health_mcp_server/tool_aed_waiting.py
hkopenai_hk_health_mcp_server-0.1.1.dist-info/licenses/LICENSE
hkopenai_hk_health_mcp_server-0.1.1.dist-info/METADATA
hkopenai_hk_health_mcp_server-0.1.1.dist-info/WHEEL
hkopenai_hk_health_mcp_server-0.1.1.dist-info/entry_points.txt
hkopenai_hk_health_mcp_server-0.1.1.dist-info/top_level.txt
hkopenai_hk_health_mcp_server-0.1.1.dist-info/RECORD
