Metadata-Version: 2.4
Name: hkopenai.hk_health_mcp_server
Version: 0.1.1
Summary: Hong Kong Health MCP Server providing financial data tools
Author-email: Neo Chow <neo@01man.com>
License-Expression: MIT
Project-URL: repository, https://github.com/hkopenai/hk-health-mcp-server.git
Classifier: Programming Language :: Python :: 3
Classifier: Operating System :: OS Independent
Requires-Python: >=3.7
License-File: LICENSE
Requires-Dist: fastmcp>=0.1.0
Requires-Dist: requests>=2.31.0
Requires-Dist: pytest>=8.2.0
Requires-Dist: pytest-cov>=6.1.1
Dynamic: license-file
